fastapi2cli/__init__.py
fastapi2cli/expose.py
fastapi2cli/fastapi_converter.py
fastapi2cli/parsers.py
fastapi2cli/typer_command_generator.py
fastapi2cli/utils.py
fastapi2cli/parameters/__init__.py
fastapi2cli/parameters/get_params_for.py
fastapi2cli/parameters/simplifier.py
fastapi2cli/parameters/validation.py
fastapi2cli/web/__init__.py
fastapi2cli/web/authentication.py
fastapi2cli/web/parameters.py
fastapi2cli/web/server_interactor.py
fastapi2cli-0.2.0.dist-info/LICENSE
fastapi2cli-0.2.0.dist-info/METADATA
fastapi2cli-0.2.0.dist-info/WHEEL
fastapi2cli-0.2.0.dist-info/top_level.txt
fastapi2cli-0.2.0.dist-info/RECORD
